zeetoo/__init__.py
zeetoo/__main__.py
zeetoo/analystex.py
zeetoo/backuper.py
zeetoo/backuper_gui.py
zeetoo/confsearch.py
zeetoo/fixgvmol.py
zeetoo/getcdx.py
zeetoo/gofproc.py
zeetoo/sdf_to_gjf.py
zeetoo-0.1.4.dist-info/LICENSE.txt
zeetoo-0.1.4.dist-info/METADATA
zeetoo-0.1.4.dist-info/WHEEL
zeetoo-0.1.4.dist-info/entry_points.txt
zeetoo-0.1.4.dist-info/top_level.txt
zeetoo-0.1.4.dist-info/RECORD
