Metadata-Version: 2.1
Name: zeetoo
Version: 0.1.4
Summary: A humble collection of various everyday utility scripts from Team II IChO PAS.
Home-page: https://github.com/mishioo/zeetoo
Author: Michał M. Więcław
Author-email: mwieclaw@icho.edu.pl
License: MIT
Platform: UNKNOWN
Classifier: Programming Language :: Python :: 3
Classifier: License :: OSI Approved :: MIT License
Classifier: Intended Audience :: Science/Research
Classifier: Topic :: Scientific/Engineering
Classifier: Development Status :: 4 - Beta
Requires-Dist: openpyxl
Requires-Dist: python-docx
Requires-Dist: olefile
